cinestats/VERSION
cinestats/__init__.py
cinestats/movie.py
cinestats/data/example.csv
cinestats/tests/__init__.py
cinestats/tests/test_movie.py
cinestats-0.0.2.dist-info/LICENSE
cinestats-0.0.2.dist-info/METADATA
cinestats-0.0.2.dist-info/WHEEL
cinestats-0.0.2.dist-info/top_level.txt
cinestats-0.0.2.dist-info/RECORD
