Metadata-Version: 2.1
Name: cinestats
Version: 0.0.2
Summary: Analyse and visualise statistics around movies and cinema.
Home-page: https://github.com/lkluft/cinestats
Author: Lukas Kluft
Author-email: lukas.kluft@gmail.com
License: GPL-3.0
Platform: UNKNOWN
Classifier: Intended Audience :: End Users/Desktop
Classifier: Intended Audience :: Other Audience
Classifier: License :: OSI Approved :: GNU General Public License v3 (GPLv3)
Classifier: Programming Language :: Python :: 3.5
Classifier: Programming Language :: Python :: 3.6
Classifier: Programming Language :: Python :: 3.7
Classifier: Programming Language :: Python :: 3.8
Requires-Python: >=3.6
Requires-Dist: matplotlib
Requires-Dist: numpy
Provides-Extra: tests
Requires-Dist: flake8 ; extra == 'tests'
Requires-Dist: pytest ; extra == 'tests'
